whohostwho/__init__.py
whohostwho/data_acquisition.py
whohostwho-0.1.1.dist-info/LICENSE
whohostwho-0.1.1.dist-info/METADATA
whohostwho-0.1.1.dist-info/WHEEL
whohostwho-0.1.1.dist-info/entry_points.txt
whohostwho-0.1.1.dist-info/top_level.txt
whohostwho-0.1.1.dist-info/RECORD
